shapboost/__init__.py
shapboost/shapboost_estimator.py
shapboost/shapboost_regressor.py
shapboost/shapboost_survival_regressor.py
shapboost/helpers/__init__.py
shapboost/helpers/random_forest.py
shapboost/helpers/xgb_survival_regressor.py
shapboost-1.0.1.dist-info/METADATA
shapboost-1.0.1.dist-info/WHEEL
shapboost-1.0.1.dist-info/top_level.txt
shapboost-1.0.1.dist-info/RECORD
