Metadata-Version: 2.1
Name: shapboost
Version: 1.0.1
Summary: A Python package for the SHAPBoost feature selection algorithm
Home-page: https://github.com/O-T-O-Z/SHAPBoost
Author: Ömer Tarik Özyilmaz, Tamas Szili-Török
Author-email: o.t.ozyilmaz@umcg.nl, t.szili-torok@umcg.nl
Keywords: Feature Selection,Boosting,SHAPBoost
Classifier: Development Status :: 4 - Beta
Classifier: Intended Audience :: Developers
Classifier: Topic :: Software Development :: Build Tools
Classifier: Programming Language :: Python :: 3.11
Requires-Python: >=3.10, <4
Requires-Dist: numpy<2.0,>=1.26
Requires-Dist: shap~=0.45
Requires-Dist: lifelines<1.0,>=0.26
Requires-Dist: pytest<8.0,>=7.0
Requires-Dist: xgboost<3.0,>=2.0
Requires-Dist: scipy<2.0,>=1.13
